Metadata-Version: 2.1
Name: dfysetters
Version: 0.1.4.10
Summary: This is a library to be used with the dfysetters.com team. It allows us to analyse our messages and extract data from them
Home-page: https://github.com/louisrae
Author: Louis-Rae
Author-email: louisrae@settersandspecialists.com
License: MIT
Download-URL: https://github.com/louisrae/team_scripts/archive/refs/tags/v0.2.8alpha.tar.gz
Keywords: data,tracking,pandas
Platform: UNKNOWN
Classifier: Development Status :: 3 - Alpha
Classifier: Intended Audience :: Developers
Classifier: Topic :: Software Development :: Build Tools
Classifier: License :: OSI Approved :: MIT License
Classifier: Programming Language :: Python :: 3
Classifier: Programming Language :: Python :: 3.4
Classifier: Programming Language :: Python :: 3.5
Classifier: Programming Language :: Python :: 3.6
License-File: LICENSE.txt
